{"cameraMode":{"drawMode":0,"name":"Shaded","section":"Shading Mode"},"sceneLighting":true,"audioPlay":false,"sceneViewState":{"showFog":true,"showMaterialUpdate":false,"showSkybox":true,"showFlares":true,"showImageEffects":true,"showParticleSystems":true},"in2DMode":false,"pivot":{"x":0.1591644287109375,"y":0.5608974099159241,"z":-0.3877373933792114},"rotation":{"x":-0.2948291301727295,"y":0.028084713965654374,"z":-0.008669523522257805,"w":-0.9550979137420654},"size":1.3764679431915284,"orthographic":false}